amzn_sp_api-1.5.0.dist-info/licenses/LICENSE
spapi/__init__.py
spapi/api_client.py
spapi/client.py
spapi/configuration.py
spapi/rest.py
spapi/api/__init__.py
spapi/api/apluscontent_v2020_11_01/__init__.py
spapi/api/apluscontent_v2020_11_01/aplus_content_api.py
spapi/api/appintegrations_v2024_04_01/__init__.py
spapi/api/appintegrations_v2024_04_01/app_integrations_api.py
spapi/api/applications_v2023_11_30/__init__.py
spapi/api/applications_v2023_11_30/applications_api.py
spapi/api/awd_v2024_05_09/__init__.py
spapi/api/awd_v2024_05_09/awd_api.py
spapi/api/catalogitems_v2022_04_01/__init__.py
spapi/api/catalogitems_v2022_04_01/catalog_api.py
spapi/api/customer_feedback_2024_06_01/__init__.py
spapi/api/customer_feedback_2024_06_01/customer_feedback_api.py
spapi/api/datakiosk_v2023_11_15/__init__.py
spapi/api/datakiosk_v2023_11_15/queries_api.py
spapi/api/easyship_v2022_03_23/__init__.py
spapi/api/easyship_v2022_03_23/easy_ship_api.py
spapi/api/fba_eligibility_v1/__init__.py
spapi/api/fba_eligibility_v1/fba_inbound_eligibility_api.py
spapi/api/fba_inventory_v1/__init__.py
spapi/api/fba_inventory_v1/fba_inventory_api.py
spapi/api/feeds_v2021_06_30/__init__.py
spapi/api/feeds_v2021_06_30/feeds_api.py
spapi/api/finances_v0/__init__.py
spapi/api/finances_v0/finances_v0_api.py
spapi/api/finances_v2024_06_19/__init__.py
spapi/api/finances_v2024_06_19/finances_v2024_api.py
spapi/api/fulfillment_inbound_v0/__init__.py
spapi/api/fulfillment_inbound_v0/fba_inbound_v0_api.py
spapi/api/fulfillment_inbound_v2024_03_20/__init__.py
spapi/api/fulfillment_inbound_v2024_03_20/fba_inbound_api.py
spapi/api/fulfillment_outbound_v2020_07_01/__init__.py
spapi/api/fulfillment_outbound_v2020_07_01/fba_outbound_api.py
spapi/api/invoices_v2024_06_19/__init__.py
spapi/api/invoices_v2024_06_19/invoices_api.py
spapi/api/listings_items_v2021_08_01/__init__.py
spapi/api/listings_items_v2021_08_01/listings_api.py
spapi/api/listings_restrictions_v2021_08_01/__init__.py
spapi/api/listings_restrictions_v2021_08_01/listings_restrictions_api.py
amzn_sp_api-1.5.0.dist-info/METADATA
amzn_sp_api-1.5.0.dist-info/WHEEL
amzn_sp_api-1.5.0.dist-info/top_level.txt
amzn_sp_api-1.5.0.dist-info/RECORD
