Metadata-Version: 2.4
Name: amzn-sp-api
Version: 1.5.0
Summary: The Selling Partner API Python SDK enables you to easily connect to and work with Amazon SP-API.
Author: Amazon
License-Expression: Apache-2.0
Project-URL: Homepage, https://developer-docs.amazon.com/sp-api/
Project-URL: Documentation, https://developer-docs.amazon.com/sp-api/docs/sp-api-sdks
Project-URL: Repository, https://github.com/amzn/selling-partner-api-sdk
Project-URL: Issues, https://github.com/amzn/selling-partner-api-sdk/issues
Keywords: spapi,spapi sdk,sp-api sdk,selling partner api sdk,amazon-spapi,amazon selling partner api
Classifier: Programming Language :: Python :: 3
Classifier: Operating System :: OS Independent
Requires-Python: >=3.9
License-File: LICENSE
Requires-Dist: urllib3<3.0.0,>=2.1.0
Requires-Dist: certifi>=2025.1.31
Requires-Dist: requests>=2.32.3
Requires-Dist: six>=1.17.0
Dynamic: license-file
